secondhandsongs/__init__.py
secondhandsongs/api.py
secondhandsongs/auth.py
secondhandsongs/dataset.py
secondhandsongs/download.py
secondhandsongs/models.py
secondhandsongs-1.0.1.dist-info/LICENSE.txt
secondhandsongs-1.0.1.dist-info/METADATA
secondhandsongs-1.0.1.dist-info/WHEEL
secondhandsongs-1.0.1.dist-info/top_level.txt
secondhandsongs-1.0.1.dist-info/RECORD
