Metadata-Version: 2.1
Name: secondhandsongs
Version: 1.0.1
Summary: Python API Wrapper for SecondHandSongs.com API
Home-page: https://github.com/arthurtofani/secondhandsongs/
Author: Arthur Tofani
Author-email: Arthur Tofani <gramofone@gmail.com>
License: MIT
Project-URL: SecondHandSongs.com, https://secondhandsongs.com/
Platform: any
Classifier: Programming Language :: Python :: 3
Classifier: License :: OSI Approved :: MIT License
Classifier: Operating System :: OS Independent
Requires-Python: >=3.7
License-File: LICENSE.txt
Requires-Dist: python-dotenv
Requires-Dist: diskcache
Requires-Dist: youtube-dl
Requires-Dist: tqdm
Requires-Dist: importlib-metadata ; python_version < "3.8"
Provides-Extra: testing
Requires-Dist: setuptools ; extra == 'testing'
Requires-Dist: dotenv ; extra == 'testing'
Requires-Dist: pytest ; extra == 'testing'
Requires-Dist: pytest-cov ; extra == 'testing'
